sema4ai_http/__init__.py
sema4ai_http/py.typed
sema4ai_http/types.py
sema4ai_http_helper-2.1.0.dist-info/LICENSE
sema4ai_http_helper-2.1.0.dist-info/METADATA
sema4ai_http_helper-2.1.0.dist-info/WHEEL
sema4ai_http_helper-2.1.0.dist-info/RECORD
