Metadata-Version: 2.3
Name: sema4ai-http-helper
Version: 2.1.0
Summary: HTTP library that enables the use of OS certificate stores when working behind MITM firewalls
License: Apache-2.0
Author: Kari H.
Author-email: kari@sema4.ai
Requires-Python: >=3.10,<4.0
Classifier: License :: OSI Approved :: Apache Software License
Classifier: Programming Language :: Python :: 3
Classifier: Programming Language :: Python :: 3.10
Classifier: Programming Language :: Python :: 3.11
Classifier: Programming Language :: Python :: 3.12
Classifier: Programming Language :: Python :: 3.13
Requires-Dist: pyyaml (>=5.0)
Requires-Dist: truststore (==0.9.2)
Requires-Dist: types-PyYAML (>=6.0.0)
Requires-Dist: urllib3 (>=2.2.2)
Project-URL: Repository, https://github.com/sema4ai/actions/
